conda_s3_sync/__init__.py
conda_s3_sync/main.py
conda_s3_sync-0.2.0.dist-info/DESCRIPTION.rst
conda_s3_sync-0.2.0.dist-info/METADATA
conda_s3_sync-0.2.0.dist-info/RECORD
conda_s3_sync-0.2.0.dist-info/WHEEL
conda_s3_sync-0.2.0.dist-info/entry_points.txt
conda_s3_sync-0.2.0.dist-info/metadata.json
conda_s3_sync-0.2.0.dist-info/top_level.txt
