Metadata-Version: 2.0
Name: conda-s3-sync
Version: 0.2.0
Summary: Synchronize Anaconda environments to/from Amazon S3
Home-page: https://github.com/Cobliteam/conda-s3-sync
Author: Daniel Miranda
Author-email: daniel@cobli.co
License: MIT
Download-URL: https://github.com/Cobliteam/conda-s3-sync/archive/0.2.0.tar.gz
Keywords: conda anaconda aws s3
Platform: UNKNOWN
Requires-Dist: boto3
Requires-Dist: iso8601
Requires-Dist: pyyaml
